README.md
setup.py
algo/__init__.py
algo/hello.py
algo900.egg-info/PKG-INFO
algo900.egg-info/SOURCES.txt
algo900.egg-info/dependency_links.txt
algo900.egg-info/top_level.txt