Metadata-Version: 2.1
Name: algo900
Version: 0.257
Summary: Python version of Synthetic difference in differences
Classifier: Programming Language :: Python :: 3
Classifier: License :: OSI Approved :: MIT License
Classifier: Operating System :: OS Independent
